airflowgp/__init__.py
airflowgp/example_dags/greenplum.py
airflowgp/hooks/__init__.py
airflowgp/hooks/greenplum.py
airflowgp/operators/__init__.py
airflowgp/operators/greenplum.py
airflowgp/provider_info.py
airflowgp-0.0.1.dist-info/entry_points.txt
airflowgp-0.0.1.dist-info/LICENSE
airflowgp-0.0.1.dist-info/METADATA
airflowgp-0.0.1.dist-info/WHEEL
airflowgp-0.0.1.dist-info/RECORD
